dtpu-0.6.3.dist-info/METADATA
dtpu-0.6.3.dist-info/WHEEL
dtpu-0.6.3.dist-info/entry_points.txt
dtpu-0.6.3.dist-info/license_files/LICENSE
text_utils/.nfs0000000007c614e0000002fc
text_utils/mask.py
text_utils/py.typed
text_utils/cli/create_dictionary.py
text_utils/cli/__init__.py
text_utils/cli/train_bpe.py
text_utils/__init__.py
text_utils/logging.py
text_utils/version.py
text_utils/modules/optimizer.py
text_utils/modules/utils.py
text_utils/modules/scheduler.py
text_utils/modules/__init__.py
text_utils/modules/head.py
text_utils/modules/loss.py
text_utils/modules/moe.py
text_utils/modules/embedding.py
text_utils/modules/grouping.py
text_utils/modules/decoder.py
text_utils/modules/encoder.py
text_utils/tensorboard.py
text_utils/distributed.py
text_utils/inference/utils.py
text_utils/inference/__init__.py
text_utils/api/cli.py
text_utils/api/server.py
text_utils/api/utils.py
text_utils/api/__init__.py
text_utils/api/processor.py
text_utils/api/trainer.py
text_utils/api/table.py
text_utils/io.py
text_utils/hook.py
text_utils/configuration.py
text_utils/_internal.abi3.so
dtpu-0.6.3.dist-info/RECORD
