Metadata-Version: 2.1
Name: dtpu
Version: 0.6.3
Classifier: Programming Language :: Rust
Classifier: Programming Language :: Python :: 3
Classifier: Topic :: Scientific/Engineering :: Artificial Intelligence
Classifier: Topic :: Software Development :: Libraries
Classifier: Topic :: Text Processing
Classifier: Topic :: Utilities
Requires-Dist: torch >=2.3
Requires-Dist: einops >=0.8
Requires-Dist: numpy >=1.26
Requires-Dist: pyyaml >=6.0
Requires-Dist: tqdm >=4.66
Requires-Dist: tensorboard >=2.16
Requires-Dist: fastapi >=0.115
Requires-Dist: uvicorn >=0.34
Requires-Dist: requests >=2.31
Requires-Dist: termcolor >=2.4
Requires-Dist: grammar-utils >=0.1
Requires-Dist: pytest >=8.0 ; extra == 'test'
Requires-Dist: bitsandbytes >=0.42 ; extra == 'low-precision'
Provides-Extra: test
Provides-Extra: low-precision
License-File: LICENSE
Summary: Utilities for text processing tasks with Deep NLP
Keywords: nlp,utilities,text,processing
Author-email: Sebastian Walter <swalter@cs.uni-freiburg.de>
Requires-Python: >=3.10
Project-URL: Github, https://github.com/ad-freiburg/text-utils
